erkr_semver_test3/__init__.py
erkr_semver_test3/main.py
erkr_semver_test3-0.1.0.dist-info/WHEEL
erkr_semver_test3-0.1.0.dist-info/METADATA
erkr_semver_test3-0.1.0.dist-info/RECORD
