Metadata-Version: 2.1
Name: erkr-semver-test3
Version: 0.1.0
Summary: This is the decription
Author: Eran Kricheli
Author-email: eran.kricheli@frontegg.com
Requires-Python: >=3.7,<4.0
Classifier: Programming Language :: Python :: 3
Classifier: Programming Language :: Python :: 3.7
Classifier: Programming Language :: Python :: 3.8
Classifier: Programming Language :: Python :: 3.9
Classifier: Programming Language :: Python :: 3.10
Classifier: Programming Language :: Python :: 3.11
Requires-Dist: Flask (>=2.2.2,<3.0.0)
Requires-Dist: fastapi (>=0.85.1,<0.86.0)
